{"config":{"output_file":null,"full_docs":false,"pub_only":true,"reachable_only":true,"distro_crate":false,"signatures":false,"borrow_data":false},"version":"0.19.0","compilation":{"directory":"/home/lzw/.cargo/registry/src/github.com-1ecc6299db9ec823/wasm-gc-api-0.1.11","program":"/home/lzw/.rustup/toolchains/nightly-2020-10-06-x86_64-unknown-linux-gnu/bin/rls","arguments":["--crate-name","wasm_gc","/home/lzw/.cargo/registry/src/github.com-1ecc6299db9ec823/wasm-gc-api-0.1.11/src/lib.rs","--json=diagnostic-rendered-ansi,artifacts","--crate-type","lib","--emit=dep-info,metadata,link","-C","embed-bitcode=no","-C","debuginfo=2","-C","metadata=614bf1927e394622","-C","extra-filename=-614bf1927e394622","--out-dir","/home/lzw/code/rust/advance-lecture-04-ocw/lecture-demo/runtime/target/rls/debug/deps","-L","dependency=/home/lzw/code/rust/advance-lecture-04-ocw/lecture-demo/runtime/target/rls/debug/deps","--extern","log=/home/lzw/code/rust/advance-lecture-04-ocw/lecture-demo/runtime/target/rls/debug/deps/liblog-1f194a4c9756f98f.rmeta","--extern","parity_wasm=/home/lzw/code/rust/advance-lecture-04-ocw/lecture-demo/runtime/target/rls/debug/deps/libparity_wasm-e01e9e3c38a769ba.rmeta","--extern","rustc_demangle=/home/lzw/code/rust/advance-lecture-04-ocw/lecture-demo/runtime/target/rls/debug/deps/librustc_demangle-872e0a84c7625315.rmeta","--cap-lints","allow","--error-format=json","--sysroot","/home/lzw/.rustup/toolchains/nightly-2020-10-06-x86_64-unknown-linux-gnu"],"output":"/home/lzw/code/rust/advance-lecture-04-ocw/lecture-demo/runtime/target/rls/debug/deps/libwasm_gc-614bf1927e394622.rmeta"},"prelude":{"crate_id":{"name":"wasm_gc","disambiguator":[828259850798536776,7597071987388727192]},"crate_root":"/home/lzw/.cargo/registry/src/github.com-1ecc6299db9ec823/wasm-gc-api-0.1.11/src","external_crates":[{"file_name":"/home/lzw/.cargo/registry/src/github.com-1ecc6299db9ec823/wasm-gc-api-0.1.11/src/lib.rs","num":1,"id":{"name":"std","disambiguator":[12552152252844610669,861143519395295934]}},{"file_name":"/home/lzw/.cargo/registry/src/github.com-1ecc6299db9ec823/wasm-gc-api-0.1.11/src/lib.rs","num":2,"id":{"name":"core","disambiguator":[6613225743082300914,1742833353142201501]}},{"file_name":"/home/lzw/.cargo/registry/src/github.com-1ecc6299db9ec823/wasm-gc-api-0.1.11/src/lib.rs","num":3,"id":{"name":"compiler_builtins","disambiguator":[11975364352078366518,17024437125936897165]}},{"file_name":"/home/lzw/.cargo/registry/src/github.com-1ecc6299db9ec823/wasm-gc-api-0.1.11/src/lib.rs","num":4,"id":{"name":"rustc_std_workspace_core","disambiguator":[7052056008796586215,10378193753915807487]}},{"file_name":"/home/lzw/.cargo/registry/src/github.com-1ecc6299db9ec823/wasm-gc-api-0.1.11/src/lib.rs","num":5,"id":{"name":"alloc","disambiguator":[7266508812970390764,1104721975748785438]}},{"file_name":"/home/lzw/.cargo/registry/src/github.com-1ecc6299db9ec823/wasm-gc-api-0.1.11/src/lib.rs","num":6,"id":{"name":"libc","disambiguator":[6114913909297575976,2747657943747640239]}},{"file_name":"/home/lzw/.cargo/registry/src/github.com-1ecc6299db9ec823/wasm-gc-api-0.1.11/src/lib.rs","num":7,"id":{"name":"unwind","disambiguator":[17650494196611787224,16696351671010573705]}},{"file_name":"/home/lzw/.cargo/registry/src/github.com-1ecc6299db9ec823/wasm-gc-api-0.1.11/src/lib.rs","num":8,"id":{"name":"cfg_if","disambiguator":[9336778117618987315,17870517156373193216]}},{"file_name":"/home/lzw/.cargo/registry/src/github.com-1ecc6299db9ec823/wasm-gc-api-0.1.11/src/lib.rs","num":9,"id":{"name":"hashbrown","disambiguator":[17103378408486634939,751433449546080727]}},{"file_name":"/home/lzw/.cargo/registry/src/github.com-1ecc6299db9ec823/wasm-gc-api-0.1.11/src/lib.rs","num":10,"id":{"name":"rustc_std_workspace_alloc","disambiguator":[10975069866030769009,5505173346458313804]}},{"file_name":"/home/lzw/.cargo/registry/src/github.com-1ecc6299db9ec823/wasm-gc-api-0.1.11/src/lib.rs","num":11,"id":{"name":"rustc_demangle","disambiguator":[6334346674486718091,8161957233453149106]}},{"file_name":"/home/lzw/.cargo/registry/src/github.com-1ecc6299db9ec823/wasm-gc-api-0.1.11/src/lib.rs","num":12,"id":{"name":"addr2line","disambiguator":[9975713641904480798,7580100659723909163]}},{"file_name":"/home/lzw/.cargo/registry/src/github.com-1ecc6299db9ec823/wasm-gc-api-0.1.11/src/lib.rs","num":13,"id":{"name":"gimli","disambiguator":[13017381940559774955,1473560800469322545]}},{"file_name":"/home/lzw/.cargo/registry/src/github.com-1ecc6299db9ec823/wasm-gc-api-0.1.11/src/lib.rs","num":14,"id":{"name":"object","disambiguator":[18046481696643307721,13304330266021309686]}},{"file_name":"/home/lzw/.cargo/registry/src/github.com-1ecc6299db9ec823/wasm-gc-api-0.1.11/src/lib.rs","num":15,"id":{"name":"miniz_oxide","disambiguator":[16808540700296544273,10362068119654760402]}},{"file_name":"/home/lzw/.cargo/registry/src/github.com-1ecc6299db9ec823/wasm-gc-api-0.1.11/src/lib.rs","num":16,"id":{"name":"adler","disambiguator":[10687136976133547149,15343372157523177244]}},{"file_name":"/home/lzw/.cargo/registry/src/github.com-1ecc6299db9ec823/wasm-gc-api-0.1.11/src/lib.rs","num":17,"id":{"name":"panic_unwind","disambiguator":[11646022853023642053,10781225934013639530]}},{"file_name":"/home/lzw/.cargo/registry/src/github.com-1ecc6299db9ec823/wasm-gc-api-0.1.11/src/lib.rs","num":18,"id":{"name":"parity_wasm","disambiguator":[16109877571363453008,12378546683981497443]}},{"file_name":"/home/lzw/.cargo/registry/src/github.com-1ecc6299db9ec823/wasm-gc-api-0.1.11/src/lib.rs","num":19,"id":{"name":"byteorder","disambiguator":[11157807316925877495,15800711268815759532]}},{"file_name":"/home/lzw/.cargo/registry/src/github.com-1ecc6299db9ec823/wasm-gc-api-0.1.11/src/lib.rs","num":20,"id":{"name":"log","disambiguator":[17656527568527509774,2025014967732049514]}},{"file_name":"/home/lzw/.cargo/registry/src/github.com-1ecc6299db9ec823/wasm-gc-api-0.1.11/src/lib.rs","num":21,"id":{"name":"cfg_if","disambiguator":[6744701999438140601,15404422640856133991]}},{"file_name":"/home/lzw/.cargo/registry/src/github.com-1ecc6299db9ec823/wasm-gc-api-0.1.11/src/lib.rs","num":22,"id":{"name":"rustc_demangle","disambiguator":[10080092189845174741,5198254188780218229]}}],"span":{"file_name":"/home/lzw/.cargo/registry/src/github.com-1ecc6299db9ec823/wasm-gc-api-0.1.11/src/lib.rs","byte_start":0,"byte_end":3992,"line_start":1,"line_end":138,"column_start":1,"column_end":2}},"imports":[{"kind":"Use","ref_id":{"krate":0,"index":180},"span":{"file_name":"/home/lzw/.cargo/registry/src/github.com-1ecc6299db9ec823/wasm-gc-api-0.1.11/src/lib.rs","byte_start":265,"byte_end":270,"line_start":20,"line_end":20,"column_start":16,"column_end":21},"alias_span":null,"name":"Error","value":"","parent":{"krate":0,"index":0}}],"defs":[{"kind":"Mod","id":{"krate":0,"index":0},"span":{"file_name":"/home/lzw/.cargo/registry/src/github.com-1ecc6299db9ec823/wasm-gc-api-0.1.11/src/lib.rs","byte_start":0,"byte_end":3992,"line_start":1,"line_end":138,"column_start":1,"column_end":2},"name":"","qualname":"::","value":"/home/lzw/.cargo/registry/src/github.com-1ecc6299db9ec823/wasm-gc-api-0.1.11/src/lib.rs","parent":null,"children":[{"krate":0,"index":1},{"krate":0,"index":2},{"krate":0,"index":3},{"krate":0,"index":4},{"krate":0,"index":5},{"krate":0,"index":6},{"krate":0,"index":111},{"krate":0,"index":120},{"krate":0,"index":133},{"krate":0,"index":134},{"krate":0,"index":135},{"krate":0,"index":136},{"krate":0,"index":137},{"krate":0,"index":138},{"krate":0,"index":139},{"krate":0,"index":140},{"krate":0,"index":141},{"krate":0,"index":144},{"krate":0,"index":147},{"krate":0,"index":158},{"krate":0,"index":162},{"krate":0,"index":165},{"krate":0,"index":167}],"decl_id":null,"docs":"","sig":null,"attributes":[]},{"kind":"Struct","id":{"krate":0,"index":180},"span":{"file_name":"/home/lzw/.cargo/registry/src/github.com-1ecc6299db9ec823/wasm-gc-api-0.1.11/src/error.rs","byte_start":31919,"byte_end":31924,"line_start":7,"line_end":7,"column_start":12,"column_end":17},"name":"Error","qualname":"::error::Error","value":"","parent":null,"children":[],"decl_id":null,"docs":" The error type for garbage collecting webassembly bytecode.\n","sig":null,"attributes":[{"value":"/ The error type for garbage collecting webassembly bytecode.","span":{"file_name":"/home/lzw/.cargo/registry/src/github.com-1ecc6299db9ec823/wasm-gc-api-0.1.11/src/error.rs","byte_start":31827,"byte_end":31890,"line_start":5,"line_end":5,"column_start":1,"column_end":64}}]},{"kind":"Struct","id":{"krate":0,"index":141},"span":{"file_name":"/home/lzw/.cargo/registry/src/github.com-1ecc6299db9ec823/wasm-gc-api-0.1.11/src/lib.rs","byte_start":284,"byte_end":290,"line_start":22,"line_end":22,"column_start":12,"column_end":18},"name":"Config","qualname":"::Config","value":"Config {  }","parent":null,"children":[{"krate":0,"index":142},{"krate":0,"index":143}],"decl_id":null,"docs":"","sig":null,"attributes":[]},{"kind":"Struct","id":{"krate":0,"index":144},"span":{"file_name":"/home/lzw/.cargo/registry/src/github.com-1ecc6299db9ec823/wasm-gc-api-0.1.11/src/lib.rs","byte_start":349,"byte_end":357,"line_start":27,"line_end":27,"column_start":12,"column_end":20},"name":"GcResult","qualname":"::GcResult","value":"","parent":null,"children":[],"decl_id":null,"docs":"","sig":null,"attributes":[]},{"kind":"Method","id":{"krate":0,"index":148},"span":{"file_name":"/home/lzw/.cargo/registry/src/github.com-1ecc6299db9ec823/wasm-gc-api-0.1.11/src/lib.rs","byte_start":470,"byte_end":473,"line_start":31,"line_end":31,"column_start":12,"column_end":15},"name":"new","qualname":"<Config>::new","value":"pub fn new() -> Config","parent":null,"children":[],"decl_id":null,"docs":" Creates a blank slate of configuration, ready to gc wasm files.\n","sig":null,"attributes":[{"value":"/ Creates a blank slate of configuration, ready to gc wasm files.","span":{"file_name":"/home/lzw/.cargo/registry/src/github.com-1ecc6299db9ec823/wasm-gc-api-0.1.11/src/lib.rs","byte_start":391,"byte_end":458,"line_start":30,"line_end":30,"column_start":5,"column_end":72}}]},{"kind":"Method","id":{"krate":0,"index":149},"span":{"file_name":"/home/lzw/.cargo/registry/src/github.com-1ecc6299db9ec823/wasm-gc-api-0.1.11/src/lib.rs","byte_start":685,"byte_end":693,"line_start":40,"line_end":40,"column_start":12,"column_end":20},"name":"demangle","qualname":"<Config>::demangle","value":"pub fn demangle(&mut Self, bool) -> &mut Self","parent":null,"children":[],"decl_id":null,"docs":" Configures whether or not this will demangle symbols as part of the gc\n pass.\n","sig":null,"attributes":[{"value":"/ Configures whether or not this will demangle symbols as part of the gc","span":{"file_name":"/home/lzw/.cargo/registry/src/github.com-1ecc6299db9ec823/wasm-gc-api-0.1.11/src/lib.rs","byte_start":585,"byte_end":659,"line_start":38,"line_end":38,"column_start":5,"column_end":79}},{"value":"/ pass.","span":{"file_name":"/home/lzw/.cargo/registry/src/github.com-1ecc6299db9ec823/wasm-gc-api-0.1.11/src/lib.rs","byte_start":664,"byte_end":673,"line_start":39,"line_end":39,"column_start":5,"column_end":14}}]},{"kind":"Method","id":{"krate":0,"index":150},"span":{"file_name":"/home/lzw/.cargo/registry/src/github.com-1ecc6299db9ec823/wasm-gc-api-0.1.11/src/lib.rs","byte_start":869,"byte_end":879,"line_start":46,"line_end":46,"column_start":12,"column_end":22},"name":"keep_debug","qualname":"<Config>::keep_debug","value":"pub fn keep_debug(&mut Self, bool) -> &mut Self","parent":null,"children":[],"decl_id":null,"docs":" Configures whether or not debug sections will be preserved.\n","sig":null,"attributes":[{"value":"/ Configures whether or not debug sections will be preserved.","span":{"file_name":"/home/lzw/.cargo/registry/src/github.com-1ecc6299db9ec823/wasm-gc-api-0.1.11/src/lib.rs","byte_start":794,"byte_end":857,"line_start":45,"line_end":45,"column_start":5,"column_end":68}}]},{"kind":"Method","id":{"krate":0,"index":151},"span":{"file_name":"/home/lzw/.cargo/registry/src/github.com-1ecc6299db9ec823/wasm-gc-api-0.1.11/src/lib.rs","byte_start":1142,"byte_end":1144,"line_start":54,"line_end":54,"column_start":12,"column_end":14},"name":"gc","qualname":"<Config>::gc","value":"pub fn gc(&mut Self, &[u8]) -> Result<Vec<u8>, Error>","parent":null,"children":[],"decl_id":null,"docs":" Runs gc passes over the wasm input module `input`, returning the\n serialized output.\n","sig":null,"attributes":[{"value":"/ Runs gc passes over the wasm input module `input`, returning the","span":{"file_name":"/home/lzw/.cargo/registry/src/github.com-1ecc6299db9ec823/wasm-gc-api-0.1.11/src/lib.rs","byte_start":986,"byte_end":1054,"line_start":51,"line_end":51,"column_start":5,"column_end":73}},{"value":"/ serialized output.","span":{"file_name":"/home/lzw/.cargo/registry/src/github.com-1ecc6299db9ec823/wasm-gc-api-0.1.11/src/lib.rs","byte_start":1059,"byte_end":1081,"line_start":52,"line_end":52,"column_start":5,"column_end":27}}]},{"kind":"Method","id":{"krate":0,"index":153},"span":{"file_name":"/home/lzw/.cargo/registry/src/github.com-1ecc6299db9ec823/wasm-gc-api-0.1.11/src/lib.rs","byte_start":1276,"byte_end":1279,"line_start":58,"line_end":58,"column_start":12,"column_end":15},"name":"run","qualname":"<Config>::run","value":"pub fn run<T: Any, impl FnOnce(T) -> Vec<u8>: FnOnce(T) ->\n           Vec<u8>>(&mut Self, T, impl FnOnce(T) -> Vec<u8>)\n-> Result<GcResult, Error>","parent":null,"children":[],"decl_id":null,"docs":"","sig":null,"attributes":[]},{"kind":"Method","id":{"krate":0,"index":159},"span":{"file_name":"/home/lzw/.cargo/registry/src/github.com-1ecc6299db9ec823/wasm-gc-api-0.1.11/src/lib.rs","byte_start":2419,"byte_end":2430,"line_start":90,"line_end":90,"column_start":12,"column_end":23},"name":"into_module","qualname":"<GcResult>::into_module","value":"pub fn into_module<T: Any>(Self) -> Result<T, Self>","parent":null,"children":[],"decl_id":null,"docs":" Attepts to downcast this `GcResult` into an instance of\n `parity_wasm::Module`.","sig":null,"attributes":[{"value":"/ Attepts to downcast this `GcResult` into an instance of","span":{"file_name":"/home/lzw/.cargo/registry/src/github.com-1ecc6299db9ec823/wasm-gc-api-0.1.11/src/lib.rs","byte_start":2085,"byte_end":2144,"line_start":84,"line_end":84,"column_start":5,"column_end":64}},{"value":"/ `parity_wasm::Module`.","span":{"file_name":"/home/lzw/.cargo/registry/src/github.com-1ecc6299db9ec823/wasm-gc-api-0.1.11/src/lib.rs","byte_start":2149,"byte_end":2175,"line_start":85,"line_end":85,"column_start":5,"column_end":31}},{"value":"/","span":{"file_name":"/home/lzw/.cargo/registry/src/github.com-1ecc6299db9ec823/wasm-gc-api-0.1.11/src/lib.rs","byte_start":2180,"byte_end":2183,"line_start":86,"line_end":86,"column_start":5,"column_end":8}},{"value":"/ If your crate's `parity_wasm` crate is a different version than this","span":{"file_name":"/home/lzw/.cargo/registry/src/github.com-1ecc6299db9ec823/wasm-gc-api-0.1.11/src/lib.rs","byte_start":2188,"byte_end":2260,"line_start":87,"line_end":87,"column_start":5,"column_end":77}},{"value":"/ crate then this method will fail and you'll need to use `into_bytes`.","span":{"file_name":"/home/lzw/.cargo/registry/src/github.com-1ecc6299db9ec823/wasm-gc-api-0.1.11/src/lib.rs","byte_start":2265,"byte_end":2338,"line_start":88,"line_end":88,"column_start":5,"column_end":78}},{"value":"/ Otherwise the module is successfully extracted and returned.","span":{"file_name":"/home/lzw/.cargo/registry/src/github.com-1ecc6299db9ec823/wasm-gc-api-0.1.11/src/lib.rs","byte_start":2343,"byte_end":2407,"line_start":89,"line_end":89,"column_start":5,"column_end":69}}]},{"kind":"Method","id":{"krate":0,"index":161},"span":{"file_name":"/home/lzw/.cargo/registry/src/github.com-1ecc6299db9ec823/wasm-gc-api-0.1.11/src/lib.rs","byte_start":3000,"byte_end":3010,"line_start":107,"line_end":107,"column_start":12,"column_end":22},"name":"into_bytes","qualname":"<GcResult>::into_bytes","value":"pub fn into_bytes(Self) -> Result<Vec<u8>, Error>","parent":null,"children":[],"decl_id":null,"docs":" Convert this `GcResult` into a serialized wasm module.","sig":null,"attributes":[{"value":"/ Convert this `GcResult` into a serialized wasm module.","span":{"file_name":"/home/lzw/.cargo/registry/src/github.com-1ecc6299db9ec823/wasm-gc-api-0.1.11/src/lib.rs","byte_start":2811,"byte_end":2869,"line_start":103,"line_end":103,"column_start":5,"column_end":63}},{"value":"/","span":{"file_name":"/home/lzw/.cargo/registry/src/github.com-1ecc6299db9ec823/wasm-gc-api-0.1.11/src/lib.rs","byte_start":2874,"byte_end":2877,"line_start":104,"line_end":104,"column_start":5,"column_end":8}},{"value":"/ Returns any error that happens during serialization, which shouldn't","span":{"file_name":"/home/lzw/.cargo/registry/src/github.com-1ecc6299db9ec823/wasm-gc-api-0.1.11/src/lib.rs","byte_start":2882,"byte_end":2954,"line_start":105,"line_end":105,"column_start":5,"column_end":77}},{"value":"/ happen for valid modules.","span":{"file_name":"/home/lzw/.cargo/registry/src/github.com-1ecc6299db9ec823/wasm-gc-api-0.1.11/src/lib.rs","byte_start":2959,"byte_end":2988,"line_start":106,"line_end":106,"column_start":5,"column_end":34}}]},{"kind":"Function","id":{"krate":0,"index":162},"span":{"file_name":"/home/lzw/.cargo/registry/src/github.com-1ecc6299db9ec823/wasm-gc-api-0.1.11/src/lib.rs","byte_start":3273,"byte_end":3293,"line_start":115,"line_end":115,"column_start":8,"column_end":28},"name":"garbage_collect_file","qualname":"::garbage_collect_file","value":"pub fn garbage_collect_file<I, O>(I, O) -> Result<(), Error> where\nI: AsRef<Path>, O: AsRef<Path>","parent":null,"children":[],"decl_id":null,"docs":" Garbage collects the webassembly bytecode from `input_path` and saves it to `output_path`.\n","sig":null,"attributes":[{"value":"/ Garbage collects the webassembly bytecode from `input_path` and saves it to `output_path`.","span":{"file_name":"/home/lzw/.cargo/registry/src/github.com-1ecc6299db9ec823/wasm-gc-api-0.1.11/src/lib.rs","byte_start":3171,"byte_end":3265,"line_start":114,"line_end":114,"column_start":1,"column_end":95}}]},{"kind":"Function","id":{"krate":0,"index":167},"span":{"file_name":"/home/lzw/.cargo/registry/src/github.com-1ecc6299db9ec823/wasm-gc-api-0.1.11/src/lib.rs","byte_start":3893,"byte_end":3914,"line_start":136,"line_end":136,"column_start":8,"column_end":29},"name":"garbage_collect_slice","qualname":"::garbage_collect_slice","value":"pub fn garbage_collect_slice(&[u8]) -> Result<Vec<u8>, Error>","parent":null,"children":[],"decl_id":null,"docs":" Garbage collects given webassembly bytecode.\n","sig":null,"attributes":[{"value":"/ Garbage collects given webassembly bytecode.","span":{"file_name":"/home/lzw/.cargo/registry/src/github.com-1ecc6299db9ec823/wasm-gc-api-0.1.11/src/lib.rs","byte_start":3837,"byte_end":3885,"line_start":135,"line_end":135,"column_start":1,"column_end":49}}]}],"impls":[{"id":0,"kind":"Inherent","span":{"file_name":"/home/lzw/.cargo/registry/src/github.com-1ecc6299db9ec823/wasm-gc-api-0.1.11/src/gc.rs","byte_start":10839,"byte_end":10847,"line_start":187,"line_end":187,"column_start":10,"column_end":18},"value":"","parent":null,"children":[{"krate":0,"index":25}],"docs":"","sig":null,"attributes":[]},{"id":1,"kind":"Inherent","span":{"file_name":"/home/lzw/.cargo/registry/src/github.com-1ecc6299db9ec823/wasm-gc-api-0.1.11/src/gc.rs","byte_start":11543,"byte_end":11554,"line_start":210,"line_end":210,"column_start":10,"column_end":21},"value":"","parent":null,"children":[{"krate":0,"index":41},{"krate":0,"index":45},{"krate":0,"index":47},{"krate":0,"index":50},{"krate":0,"index":51},{"krate":0,"index":53},{"krate":0,"index":54},{"krate":0,"index":55},{"krate":0,"index":56},{"krate":0,"index":57},{"krate":0,"index":58},{"krate":0,"index":59},{"krate":0,"index":60},{"krate":0,"index":61},{"krate":0,"index":62},{"krate":0,"index":63},{"krate":0,"index":64}],"docs":"","sig":null,"attributes":[]},{"id":2,"kind":"Inherent","span":{"file_name":"/home/lzw/.cargo/registry/src/github.com-1ecc6299db9ec823/wasm-gc-api-0.1.11/src/gc.rs","byte_start":20478,"byte_end":20490,"line_start":481,"line_end":481,"column_start":10,"column_end":22},"value":"","parent":null,"children":[{"krate":0,"index":76},{"krate":0,"index":77},{"krate":0,"index":80},{"krate":0,"index":81},{"krate":0,"index":82},{"krate":0,"index":83},{"krate":0,"index":84},{"krate":0,"index":85},{"krate":0,"index":86},{"krate":0,"index":87},{"krate":0,"index":88},{"krate":0,"index":89},{"krate":0,"index":90},{"krate":0,"index":91},{"krate":0,"index":92},{"krate":0,"index":93},{"krate":0,"index":94},{"krate":0,"index":95},{"krate":0,"index":96},{"krate":0,"index":97},{"krate":0,"index":98},{"krate":0,"index":99},{"krate":0,"index":100},{"krate":0,"index":101},{"krate":0,"index":102},{"krate":0,"index":103},{"krate":0,"index":104},{"krate":0,"index":105},{"krate":0,"index":106},{"krate":0,"index":107},{"krate":0,"index":108},{"krate":0,"index":109},{"krate":0,"index":110}],"docs":"","sig":null,"attributes":[]},{"id":3,"kind":"Direct","span":{"file_name":"/home/lzw/.cargo/registry/src/github.com-1ecc6299db9ec823/wasm-gc-api-0.1.11/src/error.rs","byte_start":31966,"byte_end":31971,"line_start":9,"line_end":9,"column_start":23,"column_end":28},"value":"","parent":null,"children":[{"krate":0,"index":116}],"docs":"","sig":null,"attributes":[]},{"id":4,"kind":"Direct","span":{"file_name":"/home/lzw/.cargo/registry/src/github.com-1ecc6299db9ec823/wasm-gc-api-0.1.11/src/error.rs","byte_start":32089,"byte_end":32094,"line_start":15,"line_end":15,"column_start":23,"column_end":28},"value":"","parent":null,"children":[{"krate":0,"index":118}],"docs":"","sig":null,"attributes":[]},{"id":5,"kind":"Inherent","span":{"file_name":"/home/lzw/.cargo/registry/src/github.com-1ecc6299db9ec823/wasm-gc-api-0.1.11/src/bitvec.rs","byte_start":32392,"byte_end":32398,"line_start":11,"line_end":11,"column_start":6,"column_end":12},"value":"","parent":null,"children":[{"krate":0,"index":127},{"krate":0,"index":128},{"krate":0,"index":129}],"docs":"","sig":null,"attributes":[]},{"id":6,"kind":"Direct","span":{"file_name":"/home/lzw/.cargo/registry/src/github.com-1ecc6299db9ec823/wasm-gc-api-0.1.11/src/bitvec.rs","byte_start":33121,"byte_end":33127,"line_start":42,"line_end":42,"column_start":18,"column_end":24},"value":"","parent":null,"children":[{"krate":0,"index":132}],"docs":"","sig":null,"attributes":[]},{"id":7,"kind":"Inherent","span":{"file_name":"/home/lzw/.cargo/registry/src/github.com-1ecc6299db9ec823/wasm-gc-api-0.1.11/src/lib.rs","byte_start":378,"byte_end":384,"line_start":29,"line_end":29,"column_start":6,"column_end":12},"value":"","parent":null,"children":[{"krate":0,"index":148},{"krate":0,"index":149},{"krate":0,"index":150},{"krate":0,"index":151},{"krate":0,"index":153},{"krate":0,"index":157}],"docs":"","sig":null,"attributes":[]},{"id":8,"kind":"Inherent","span":{"file_name":"/home/lzw/.cargo/registry/src/github.com-1ecc6299db9ec823/wasm-gc-api-0.1.11/src/lib.rs","byte_start":2070,"byte_end":2078,"line_start":83,"line_end":83,"column_start":6,"column_end":14},"value":"","parent":null,"children":[{"krate":0,"index":159},{"krate":0,"index":161}],"docs":"","sig":null,"attributes":[]}],"refs":[],"macro_refs":[],"relations":[{"span":{"file_name":"/home/lzw/.cargo/registry/src/github.com-1ecc6299db9ec823/wasm-gc-api-0.1.11/src/gc.rs","byte_start":10839,"byte_end":10847,"line_start":187,"line_end":187,"column_start":10,"column_end":18},"kind":{"Impl":{"id":0}},"from":{"krate":0,"index":15},"to":{"krate":4294967295,"index":4294967295}},{"span":{"file_name":"/home/lzw/.cargo/registry/src/github.com-1ecc6299db9ec823/wasm-gc-api-0.1.11/src/gc.rs","byte_start":11543,"byte_end":11554,"line_start":210,"line_end":210,"column_start":10,"column_end":21},"kind":{"Impl":{"id":1}},"from":{"krate":0,"index":26},"to":{"krate":4294967295,"index":4294967295}},{"span":{"file_name":"/home/lzw/.cargo/registry/src/github.com-1ecc6299db9ec823/wasm-gc-api-0.1.11/src/gc.rs","byte_start":20478,"byte_end":20490,"line_start":481,"line_end":481,"column_start":10,"column_end":22},"kind":{"Impl":{"id":2}},"from":{"krate":0,"index":65},"to":{"krate":4294967295,"index":4294967295}},{"span":{"file_name":"/home/lzw/.cargo/registry/src/github.com-1ecc6299db9ec823/wasm-gc-api-0.1.11/src/error.rs","byte_start":31966,"byte_end":31971,"line_start":9,"line_end":9,"column_start":23,"column_end":28},"kind":{"Impl":{"id":3}},"from":{"krate":0,"index":180},"to":{"krate":1,"index":1720}},{"span":{"file_name":"/home/lzw/.cargo/registry/src/github.com-1ecc6299db9ec823/wasm-gc-api-0.1.11/src/error.rs","byte_start":32089,"byte_end":32094,"line_start":15,"line_end":15,"column_start":23,"column_end":28},"kind":{"Impl":{"id":4}},"from":{"krate":0,"index":180},"to":{"krate":2,"index":6568}},{"span":{"file_name":"/home/lzw/.cargo/registry/src/github.com-1ecc6299db9ec823/wasm-gc-api-0.1.11/src/bitvec.rs","byte_start":32392,"byte_end":32398,"line_start":11,"line_end":11,"column_start":6,"column_end":12},"kind":{"Impl":{"id":5}},"from":{"krate":0,"index":124},"to":{"krate":4294967295,"index":4294967295}},{"span":{"file_name":"/home/lzw/.cargo/registry/src/github.com-1ecc6299db9ec823/wasm-gc-api-0.1.11/src/bitvec.rs","byte_start":33121,"byte_end":33127,"line_start":42,"line_end":42,"column_start":18,"column_end":24},"kind":{"Impl":{"id":6}},"from":{"krate":0,"index":124},"to":{"krate":2,"index":2026}},{"span":{"file_name":"/home/lzw/.cargo/registry/src/github.com-1ecc6299db9ec823/wasm-gc-api-0.1.11/src/lib.rs","byte_start":378,"byte_end":384,"line_start":29,"line_end":29,"column_start":6,"column_end":12},"kind":{"Impl":{"id":7}},"from":{"krate":0,"index":141},"to":{"krate":4294967295,"index":4294967295}},{"span":{"file_name":"/home/lzw/.cargo/registry/src/github.com-1ecc6299db9ec823/wasm-gc-api-0.1.11/src/lib.rs","byte_start":2070,"byte_end":2078,"line_start":83,"line_end":83,"column_start":6,"column_end":14},"kind":{"Impl":{"id":8}},"from":{"krate":0,"index":144},"to":{"krate":4294967295,"index":4294967295}}]}